{
  "Prime": [
    "Prime Video",
    "Prime Music",
    "Prime Gaming",
    "Prime Reading",
    "Prime Photos",
    "Prime Wardrobe",
    "Prime Now",
    "Prime Pantry",
    "Prime Early Access",
    "Prime Family",
    "Prime Student",
    "Prime Wardrobe",
    "Prime Delivery",
    "Prime Channels",
    "Prime Shopping",
    "Prime Fresh",
    "Prime Pharmacy",
    "Prime Day",
    "Prime Samples",
    "Prime Deals"
  ],
  "Hediye": [
    "Hediye Kartları",
    "Hediye Çekleri",
    "Hediye Paketleri",
    "Hediye Sepetleri",
    "Kişiye Özel Hediyeler",
    "Yılbaşı Hediyeleri",
    "Doğum Günü Hediyeleri",
    "Sevgililer Günü Hediyeleri",
    "Anneler Günü Hediyeleri",
    "Babalar Günü Hediyeleri",
    "Düğün Hediyeleri",
    "Nişan Hediyeleri",
    "Bebek Hediyeleri",
    "Arkadaş Hediyeleri",
    "Romantik Hediyeler",
    "Kardeş Hediyeleri",
    "Öğretmen Hediyeleri",
    "Patron Hediyeleri",
    "Mezuniyet Hediyeleri",
    "Yeni İş Hediyeleri"
  ],
  "Fırsatlar": [
    "Günlük Fırsatlar",
    "Özel Fırsatlar",
    "İndirimler",
    "Yılbaşı İndirimleri",
    "Kara Cuma Fırsatları",
    "Süper Cumartesi Fırsatları",
    "Yılsonu İndirimleri",
    "Sezon Sonu İndirimleri",
    "Flash İndirimler",
    "Hafta Sonu Fırsatları",
    "Ayın Fırsatları",
    "Çılgın İndirimler",
    "Kaçırılmayacak Fırsatlar",
    "Yeni Yıl İndirimleri",
    "Sevgililer Günü İndirimleri",
    "Anneler Günü İndirimleri",
    "Babalar Günü İndirimleri",
    "Doğum Günü İndirimleri",
    "Evlilik Yıldönümü Fırsatları",
    "Büyük Fırsatlar"
  ],
  "Gıda ve İçecek": [
    "Atıştırmalıklar",
    "İçecekler",
    "Organik Ürünler",
    "Şekerlemeler",
    "Kuruyemişler",
    "Meyve ve Sebzeler",
    "Süt ve Süt Ürünleri",
    "Et ve Balık Ürünleri",
    "Konserve Ürünler",
    "Bakliyat ve Tahıllar",
    "Çay ve Kahve",
    "Enerji İçecekleri",
    "Sporcu Gıdaları",
    "Makarna ve Pirinç",
    "Soslar ve Baharatlar",
    "Hazır Yemekler",
    "Kahvaltılık Ürünler",
    "Bebek Mamaları",
    "Sağlıklı Atıştırmalıklar",
    "Dondurulmuş Gıdalar"
  ],
  "Sağlık": [
    "Ağız ve Diş Sağlığı",
    "Sağlıklı Yaşam",
    "Bebek ve Çocuk Bakımı",
    "Cilt Bakımı",
    "Saç Bakımı",
    "Göz Bakımı",
    "Kulak Bakımı",
    "Ayak Bakımı",
    "El Bakımı",
    "Vücut Bakımı",
    "Vitamin ve Mineraller",
    "Bitkisel Ürünler",
    "Medikal Ürünler",
    "Sporcu Sağlığı",
    "Gıda Takviyeleri",
    "Beslenme ve Diyet",
    "Kadın Sağlığı",
    "Erkek Sağlığı",
    "Yaşlı Bakımı",
    "Engelli Bakımı"
  ],
  "Evcil Hayvan": [
    "Köpek Ürünleri",
    "Kedi Ürünleri",
    "Kuş Ürünleri",
    "Balık Ürünleri",
    "Kemirgen Ürünleri",
    "Sürüngen Ürünleri",
    "Köpek Mamaları",
    "Kedi Mamaları",
    "Kuş Yemleri",
    "Balık Yemleri",
    "Kemirgen Yemleri",
    "Sürüngen Yemleri",
    "Köpek Oyuncakları",
    "Kedi Oyuncakları",
    "Kuş Oyuncakları",
    "Balık Tankları",
    "Kemirgen Kafesleri",
    "Sürüngen Kafesleri",
    "Evcil Hayvan Yatakları",
    "Evcil Hayvan Bakımı"
  ],
  "Moda ve Güzellik": [
    "Kadın Giyim",
    "Erkek Giyim",
    "Güzellik Ürünleri",
    "Ayakkabılar",
    "Çantalar",
    "Aksesuarlar",
    "Kozmetik Ürünler",
    "Parfümler",
    "Cilt Bakım Ürünleri",
    "Saç Bakım Ürünleri",
    "Makyaj Ürünleri",
    "Takılar",
    "Saatler",
    "Güneş Gözlükleri",
    "Spor Giyim",
    "İç Giyim",
    "Dış Giyim",
    "Abiye Giyim",
    "Plaj Giyim",
    "Moda Trendleri"
  ],
  "Ev ve Mutfak": [
    "Mutfak Gereçleri",
    "Ev Dekorasyonu",
    "Temizlik Ürünleri",
    "Beyaz Eşyalar",
    "Mobilya",
    "Aydınlatma",
    "Bahçe Ürünleri",
    "Banyo Ürünleri",
    "Yatak Odası Ürünleri",
    "Oturma Odası Ürünleri",
    "Ev Tekstili",
    "Ev Elektroniği",
    "Depolama Ürünleri",
    "Mutfak Aletleri",
    "Yemek Takımları",
    "Çatal Bıçak Takımları",
    "Tencere ve Tavalar",
    "Mutfak Dekorasyonu",
    "Bahçe Mobilyaları",
    "Evcil Hayvan Mobilyaları"
  ]
}
